jaf/__init__.py
jaf/api.py
jaf/codata_loaders.py
jaf/console_script.py
jaf/dsl_compiler.py
jaf/dsl_parser.py
jaf/exceptions.py
jaf/io_utils.py
jaf/jaf_eval.py
jaf/json_stream.py
jaf/lazy_ops_loader.py
jaf/lazy_streams.py
jaf/mcp_server.py
jaf/path_conversion.py
jaf/path_evaluation.py
jaf/path_exceptions.py
jaf/path_operations.py
jaf/path_types.py
jaf/probabilistic.py
jaf/sexp_parser.py
jaf/streaming_loader.py
jaf/utils.py
jaf-0.8.0.dist-info/licenses/LICENSE
jaf-0.8.0.dist-info/METADATA
jaf-0.8.0.dist-info/WHEEL
jaf-0.8.0.dist-info/entry_points.txt
jaf-0.8.0.dist-info/top_level.txt
jaf-0.8.0.dist-info/RECORD
