Metadata-Version: 2.4
Name: jaf
Version: 0.8.0
Summary: JAF (Just Another Flow) - A streaming data processing system for JSON with lazy evaluation, composable operations, and a fluent API
Author-email: Alex Towell <lex@metafunctor.com>
License-Expression: MIT
Project-URL: Homepage, https://github.com/queelius/jaf
Project-URL: Documentation, https://queelius.github.io/jaf
Project-URL: Repository, https://github.com/queelius/jaf
Keywords: streaming,JSON,JSONL,lazy-evaluation,fluent-api,data-processing,pipeline,flow
Classifier: Programming Language :: Python :: 3
Classifier: Operating System :: OS Independent
License-File: LICENSE
Requires-Dist: rapidfuzz
Requires-Dist: fuzzy
Requires-Dist: lark>=1.1.0
Provides-Extra: dev
Requires-Dist: pytest; extra == "dev"
Requires-Dist: pytest-cov; extra == "dev"
Requires-Dist: pytest-asyncio; extra == "dev"
Requires-Dist: mkdocs>=1.5.0; extra == "dev"
Requires-Dist: mkdocs-material>=9.0.0; extra == "dev"
Requires-Dist: pymdown-extensions>=10.0; extra == "dev"
Provides-Extra: api
Requires-Dist: fastapi>=0.100.0; extra == "api"
Requires-Dist: uvicorn[standard]>=0.23.0; extra == "api"
Requires-Dist: pydantic>=2.0.0; extra == "api"
Requires-Dist: websockets>=11.0; extra == "api"
Provides-Extra: mcp
Requires-Dist: mcp>=0.1.0; extra == "mcp"
Dynamic: license-file
